Sorting/__init__.py
Sorting/sorting_algorithms.py
Rizwan_Hafeez-1.1.dist-info/LICENCE.txt
Rizwan_Hafeez-1.1.dist-info/METADATA
Rizwan_Hafeez-1.1.dist-info/WHEEL
Rizwan_Hafeez-1.1.dist-info/top_level.txt
Rizwan_Hafeez-1.1.dist-info/RECORD
