Metadata-Version: 2.1
Name: Rizwan-Hafeez
Version: 1.1
Summary: This package is about sorting 
Author: Rizwan Hafeez
Author-email: msdsf21m525@pucit.edu.pk
License: UNKNOWN
Platform: UNKNOWN
Classifier: Programming Language :: Python :: 3
Classifier: License :: OSI Approved :: MIT License
Classifier: Operating System :: OS Independent
License-File: LICENCE.txt
